xrmocap/__init__.py
xrmocap/version.py
xrmocap/core/__init__.py
xrmocap/core/estimation/__init__.py
xrmocap/core/estimation/base_estimator.py
xrmocap/core/estimation/builder.py
xrmocap/core/estimation/mperson_smpl_estimator.py
xrmocap/core/estimation/mview_mperson_end2end_estimator.py
xrmocap/core/estimation/mview_mperson_topdown_estimator.py
xrmocap/core/estimation/mview_sperson_smpl_estimator.py
xrmocap/core/evaluation/__init__.py
xrmocap/core/evaluation/base_evaluation.py
xrmocap/core/evaluation/bottom_up_association_evaluation.py
xrmocap/core/evaluation/builder.py
xrmocap/core/evaluation/end2end_evaluation.py
xrmocap/core/evaluation/metric_manager.py
xrmocap/core/evaluation/top_down_association_evaluation.py
xrmocap/core/evaluation/metrics/__init__.py
xrmocap/core/evaluation/metrics/base_metric.py
xrmocap/core/evaluation/metrics/builder.py
xrmocap/core/evaluation/metrics/mpjpe_metric.py
xrmocap/core/evaluation/metrics/pa_mpjpe_metric.py
xrmocap/core/evaluation/metrics/pck_metric.py
xrmocap/core/evaluation/metrics/pcp_metric.py
xrmocap/core/evaluation/metrics/precision_recall_metric.py
xrmocap/core/evaluation/metrics/prediction_matcher.py
xrmocap/core/hook/__init__.py
xrmocap/core/hook/smplify_hook/__init__.py
xrmocap/core/hook/smplify_hook/builder.py
xrmocap/core/hook/smplify_hook/smplify_base_hook.py
xrmocap/core/hook/smplify_hook/smplify_verbose_hook.py
xrmocap/core/train/__init__.py
xrmocap/core/train/builder.py
xrmocap/core/train/trainer.py
xrmocap/core/visualization/__init__.py
xrmocap/core/visualization/visualize_keypoints2d.py
xrmocap/core/visualization/visualize_keypoints3d.py
xrmocap/core/visualization/visualize_smpl.py
xrmocap/core/visualization/render/__init__.py
xrmocap/core/visualization/render/mpr_renderer.py
xrmocap/data_structure/__init__.py
xrmocap/data_structure/keypoints.py
xrmocap/data_structure/limbs.py
xrmocap/data_structure/smc_reader.py
xrmocap/data_structure/body_model/__init__.py
xrmocap/data_structure/body_model/smpl_data.py
xrmocap-0.8.0.dist-info/LICENSE
xrmocap-0.8.0.dist-info/METADATA
xrmocap-0.8.0.dist-info/WHEEL
xrmocap-0.8.0.dist-info/top_level.txt
xrmocap-0.8.0.dist-info/RECORD
