Metadata-Version: 2.1
Name: xrmocap
Version: 0.8.0
Summary: UNKNOWN
Home-page: https://github.com/openxrlab/xrmocap
Author: 
Author-email: 
License: Apache License 2.0
Platform: UNKNOWN
Classifier: Development Status :: 4 - Beta
Classifier: License :: OSI Approved :: Apache Software License
Classifier: Operating System :: OS Independent
Classifier: Programming Language :: Python :: 3
Classifier: Programming Language :: Python :: 3.6
Classifier: Programming Language :: Python :: 3.7
Classifier: Programming Language :: Python :: 3.8
Classifier: Programming Language :: Python :: 3.9
Requires-Dist: filterpy
Requires-Dist: numpy (==1.23.5)
Requires-Dist: opencv-python-headless
Requires-Dist: pre-commit
Requires-Dist: prettytable
Requires-Dist: scipy (==1.10.0)
Requires-Dist: smplx
Requires-Dist: tqdm
